phyphoxBLE/__init__.py
phyphoxBLE/ble_advertising.py
phyphoxBLE/experiment.py
phyphoxBLE/phyphoxBLE.py
phyphoxBLE-0.1.1.dist-info/COPYING
phyphoxBLE-0.1.1.dist-info/COPYING.LESSER
phyphoxBLE-0.1.1.dist-info/METADATA
phyphoxBLE-0.1.1.dist-info/WHEEL
phyphoxBLE-0.1.1.dist-info/top_level.txt
phyphoxBLE-0.1.1.dist-info/RECORD
