Metadata-Version: 2.1
Name: phyphoxBLE
Version: 0.1.1
Summary: Use phyphox to plot sensor data from your Microcontroller.
Home-page: https://github.com/phyphox/phyphox-micropython
Author: phyphox / RWTH Aachen University
Author-email: contact@phyphox.org
License: GNU Lesser General Public License 3.0
Project-URL: phyphox, https://phyphox.org
Keywords: BLE,Bluetooth,phyphox,plotting,smartphone
Classifier: Programming Language :: Python :: 3
Classifier: Programming Language :: Python :: Implementation :: MicroPython
License-File: COPYING
License-File: COPYING.LESSER
